{
  "last_updated": "2025-09-23 07:21:08",
  "depo_name": "Depo Tanjung",
  "region_name": "Region Kalimantan",
  "lob_cards": [
    {
      "name": "GPPJ",
      "achievement": "113%",
      "actual": "2.0M",
      "target": "1.8M",
      "gap": "219.4Jt",
      "vs_bp": "+1%",
      "vs_ly": "+0%",
      "vs_3lm": "+0%",
      "vs_lm": "+0%"
    },
    {
      "name": "GEN",
      "achievement": "58%",
      "actual": "126.4Jt",
      "target": "217.7Jt",
      "gap": "91.3Jt",
      "vs_bp": "+58%",
      "vs_ly": "+0%",
      "vs_3lm": "-29%",
      "vs_lm": "+0%"
    },
    {
      "name": "GBS",
      "achievement": "56%",
      "actual": "639.3Jt",
      "target": "1.2M",
      "gap": "511.0Jt",
      "vs_bp": "+56%",
      "vs_ly": "+0%",
      "vs_3lm": "-26%",
      "vs_lm": "+0%"
    },
    {
      "name": "MBR",
      "achievement": "121%",
      "actual": "41.0Jt",
      "target": "33.9Jt",
      "gap": "7.1Jt",
      "vs_bp": "+1%",
      "vs_ly": "+0%",
      "vs_3lm": "+43%",
      "vs_lm": "+0%"
    },
    {
      "name": "HGJ",
      "achievement": "24%",
      "actual": "1.2Jt",
      "target": "4.9Jt",
      "gap": "3.7Jt",
      "vs_bp": "+24%",
      "vs_ly": "+0%",
      "vs_3lm": "+50%",
      "vs_lm": "+0%"
    },
    {
      "name": "RANS",
      "achievement": "433%",
      "actual": "33.9Jt",
      "target": "7.8Jt",
      "gap": "26.1Jt",
      "vs_bp": "+4%",
      "vs_ly": "+0%",
      "vs_3lm": "-19%",
      "vs_lm": "+0%"
    },
    {
      "name": "GSJ",
      "achievement": "6%",
      "actual": "248Rb",
      "target": "4.3Jt",
      "gap": "4.0Jt",
      "vs_bp": "+6%",
      "vs_ly": "+0%",
      "vs_3lm": "-40%",
      "vs_lm": "+0%"
    },
    {
      "name": "ABBOTT",
      "achievement": "0%",
      "actual": "32.6Jt",
      "target": "0",
      "gap": "32.6Jt",
      "vs_bp": "+0%",
      "vs_ly": "+0%",
      "vs_3lm": "+3%",
      "vs_lm": "+0%"
    }
  ],
  "total_data": {
    "name": "TOTAL",
    "achievement": "90%",
    "actual": "2.8M",
    "target": "3.2M",
    "gap": "324.9Jt",
    "vs_bp": "+90%",
    "vs_ly": "+0%",
    "vs_3lm": "-8%",
    "vs_lm": "+0%"
  }
}