{"Nama Depo":"Depo Tanjung","T.CR":1028,"A.CR":1231,"Ach_CR":1.1974708171,"A.CA":76,"Ach_CA":0.061738424,"T.PC":23,"A.PC":26.1666666667,"Ach_PC":1.1376811594,"T.AC":26.1666666667,"A.AC":26.1666666667,"Ach_AC":1,"T.EC":19.625,"A.EC":18.5,"Ach_EC":0.9426751592,"T.ET":18.64375,"A.ET":12.6666666667,"Ach_ET":0.6794055202,"T.AvgSKU":22.5,"A.AvgSKU":7.9407191937,"Ach_AvgSKU":0.3529208531,"T.CAProdW":59,"A.CAProdW":8,"Ach_CAProdW":0.1355932203,"T.CAProdR":93,"A.CAProdR":25,"Ach_CAProdR":0.2688172043,"T.CAProdM":4,"A.CAProdM":1,"Ach_CAProdM":0.25,"Ach_CAProdAll":0.2181368082,"T.GPFood":5190,"A.GPFood":0,"Ach_GPFood":0,"T.GPOthers":900,"A.GPOthers":0,"Ach_GPOthers":0}
