{"Nama Depo":"Depo Tanjung","szEmployeeId":17210032876,"szname":"Asman","Tipe Salesman":"Sales Representative Mix Yudistira","Target":1103426000,"Actual":117983543.7180009782,"Ach":0.106924745,"Gap":-985442456.281998992,"Rank":4}
{"Nama Depo":"Depo Tanjung","szEmployeeId":17210037897,"szname":"Hindra","Tipe Salesman":"Sales Representative Mix Yudistira","Target":476316000,"Actual":45456256.3044390157,"Ach":0.0954329821,"Gap":-430859743.6955609918,"Rank":5}
{"Nama Depo":"Depo Tanjung","szEmployeeId":17210036369,"szname":"Muhammad Tamrin","Tipe Salesman":"Sales Representative Mix Yudistira","Target":738226000,"Actual":156250026.6411989629,"Ach":0.2116560872,"Gap":-581975973.3588010073,"Rank":2}
{"Nama Depo":"Depo Tanjung","szEmployeeId":17210037632,"szname":"Robianor","Tipe Salesman":"Sales Representative Mix Yudistira","Target":715525000,"Actual":65464489.2566490173,"Ach":0.0914915471,"Gap":-650060510.7433509827,"Rank":6}
{"Nama Depo":"Depo Tanjung","szEmployeeId":17210041467,"szname":"Doli Purnama Sari","Tipe Salesman":"Sales Representative Retailer Arjuna","Target":160142000,"Actual":31830263.1324959956,"Ach":0.1987627426,"Gap":-128311736.8675040007,"Rank":3}
{"Nama Depo":"Depo Tanjung","szEmployeeId":17210041719,"szname":"Muhammad Iqbal Purwa Atmaja","Tipe Salesman":"Sales Representative Retailer Bima","Target":102042000,"Actual":38810207.5692280233,"Ach":0.3803356223,"Gap":-63231792.4307719767,"Rank":1}
