{"Nama Depo":"Depo Tanjung","NIK SAC":17200519965,"Nama SAC":"Kisman Pidu","szEmployeeId":17210032876,"szname":"Asman","Dept":"ACQ","Tipe Salesman":"Sales Representative Wholesaler Arjuna","3LM":526098615.9334408641,"Target":522000000,"Actual":533573880.2006755471,"Ach":1.0221721843,"vs 3LM":0.0142088651,"LOB":"GPPJ","GROUP":"GPPJ","Gap":11573880.2006755471,"SO H-2":106284820.5899998248}
{"Nama Depo":"Depo Tanjung","NIK SAC":17200519965,"Nama SAC":"Kisman Pidu","szEmployeeId":17210032876,"szname":"Asman","Dept":"ACQ","Tipe Salesman":"Sales Representative Wholesaler Arjuna","3LM":64002236.1596379653,"Target":64000000,"Actual":49864891.9512699991,"Ach":0.7791389367,"vs 3LM":-0.2208882854,"LOB":"GEN","GROUP":"GEN","Gap":-14135108.0487300009,"SO H-2":7164324.4000000004}
{"Nama Depo":"Depo Tanjung","NIK SAC":17200519965,"Nama SAC":"Kisman Pidu","szEmployeeId":17210041467,"szname":"Doli Purnama Sari","Dept":"ACS","Tipe Salesman":"Sales Representative Retailer Arjuna","3LM":129094422.079105556,"Target":146000000,"Actual":119470160.9793988168,"Ach":0.8182887738,"vs 3LM":-0.0745521065,"LOB":"GPPJ","GROUP":"GPPJ","Gap":-26529839.0206011832,"SO H-2":17041519.4300000221}
{"Nama Depo":"Depo Tanjung","NIK SAC":17200519965,"Nama SAC":"Kisman Pidu","szEmployeeId":17210041467,"szname":"Doli Purnama Sari","Dept":"ACS","Tipe Salesman":"Sales Representative Retailer Arjuna","3LM":19632552.814434763,"Target":13000000,"Actual":17828722.9284380116,"Ach":1.3714402253,"vs 3LM":-0.0918795382,"LOB":"GEN","GROUP":"GEN","Gap":4828722.9284380116,"SO H-2":2187703.6500000004}
{"Nama Depo":"Depo Tanjung","NIK SAC":17200519965,"Nama SAC":"Kisman Pidu","szEmployeeId":17210037897,"szname":"Hindra","Dept":"ADD","Tipe Salesman":"Sales Representative Mix Yudistira","3LM":9509646.2051810008,"Target":13000000,"Actual":4944218.9034179999,"Ach":0.380324531,"vs 3LM":-0.4800838226,"LOB":"MBR","GROUP":"MBR","Gap":-8055781.0965820001,"SO H-2":5460190.2000000002}
{"Nama Depo":"Depo Tanjung","NIK SAC":17200519965,"Nama SAC":"Kisman Pidu","szEmployeeId":17210037897,"szname":"Hindra","Dept":"ADD","Tipe Salesman":"Sales Representative Mix Yudistira","3LM":4639220.8733333359,"Target":10700000,"Actual":5183978.7599999951,"Ach":0.4844839963,"vs 3LM":0.1174244343,"LOB":"RANS","GROUP":"OTHERS","Gap":-5516021.2400000049,"SO H-2":476613.17}
{"Nama Depo":"Depo Tanjung","NIK SAC":17200519965,"Nama SAC":"Kisman Pidu","szEmployeeId":17210037897,"szname":"Hindra","Dept":"ADD","Tipe Salesman":"Sales Representative Mix Yudistira","3LM":0.0,"Target":0,"Actual":0.0,"Ach":0.0,"vs 3LM":0.0,"LOB":"GSJ","GROUP":"OTHERS","Gap":0.0,"SO H-2":0.0}
{"Nama Depo":"Depo Tanjung","NIK SAC":17200519965,"Nama SAC":"Kisman Pidu","szEmployeeId":17210037897,"szname":"Hindra","Dept":"ADD","Tipe Salesman":"Sales Representative Mix Yudistira","3LM":331155874.098519206,"Target":395300000,"Actual":314336756.0934760571,"Ach":0.7951853177,"vs 3LM":-0.0507891278,"LOB":"GPPJ","GROUP":"GPPJ","Gap":-80963243.9065239429,"SO H-2":88185983.7399999797}
{"Nama Depo":"Depo Tanjung","NIK SAC":17200519965,"Nama SAC":"Kisman Pidu","szEmployeeId":17210037897,"szname":"Hindra","Dept":"ADD","Tipe Salesman":"Sales Representative Mix Yudistira","3LM":27749834.1036716588,"Target":28000000,"Actual":31823944.423837997,"Ach":1.1365694437,"vs 3LM":0.146815664,"LOB":"GEN","GROUP":"GEN","Gap":3823944.423837997,"SO H-2":5278431.6000000006}
{"Nama Depo":"Depo Tanjung","NIK SAC":17200519965,"Nama SAC":"Kisman Pidu","szEmployeeId":17210037897,"szname":"Hindra","Dept":"ADD","Tipe Salesman":"Sales Representative Mix Yudistira","3LM":151337395.5651555657,"Target":190000000,"Actual":127796246.7258142233,"Ach":0.6726118249,"vs 3LM":-0.1555540767,"LOB":"GBS","GROUP":"GBS","Gap":-62203753.2741857767,"SO H-2":136937655.8599999845}
{"Nama Depo":"Depo Tanjung","NIK SAC":17200519965,"Nama SAC":"Kisman Pidu","szEmployeeId":17210037897,"szname":"Hindra","Dept":"ADD","Tipe Salesman":"Sales Representative Mix Yudistira","3LM":55576.2833333333,"Target":700000,"Actual":0.0,"Ach":0.0,"vs 3LM":-1.0,"LOB":"HGJ","GROUP":"OTHERS","Gap":-700000.0,"SO H-2":0.0}
{"Nama Depo":"Depo Tanjung","NIK SAC":17200519965,"Nama SAC":"Kisman Pidu","szEmployeeId":17210042412,"szname":"Muhammad Rizky Algifari","Dept":"ADD","Tipe Salesman":"Sales Representative Mix Yudistira","3LM":935796.6977753332,"Target":9000000,"Actual":1540771.1737799998,"Ach":0.1711967971,"vs 3LM":0.6464806698,"LOB":"MBR","GROUP":"MBR","Gap":-7459228.8262200002,"SO H-2":139864.87}
{"Nama Depo":"Depo Tanjung","NIK SAC":17200519965,"Nama SAC":"Kisman Pidu","szEmployeeId":17210042412,"szname":"Muhammad Rizky Algifari","Dept":"ADD","Tipe Salesman":"Sales Representative Mix Yudistira","3LM":1401720.0033333346,"Target":7600000,"Actual":5758415.5799999982,"Ach":0.7576862605,"vs 3LM":3.1081068732,"LOB":"RANS","GROUP":"OTHERS","Gap":-1841584.4200000018,"SO H-2":402434.18}
{"Nama Depo":"Depo Tanjung","NIK SAC":17200519965,"Nama SAC":"Kisman Pidu","szEmployeeId":17210042412,"szname":"Muhammad Rizky Algifari","Dept":"ADD","Tipe Salesman":"Sales Representative Mix Yudistira","3LM":0.0,"Target":0,"Actual":0.0,"Ach":0.0,"vs 3LM":0.0,"LOB":"GSJ","GROUP":"OTHERS","Gap":0.0,"SO H-2":0.0}
{"Nama Depo":"Depo Tanjung","NIK SAC":17200519965,"Nama SAC":"Kisman Pidu","szEmployeeId":17210042412,"szname":"Muhammad Rizky Algifari","Dept":"ADD","Tipe Salesman":"Sales Representative Mix Yudistira","3LM":106111373.1877273023,"Target":289000000,"Actual":237428053.3422890604,"Ach":0.8215503576,"vs 3LM":1.2375363376,"LOB":"GPPJ","GROUP":"GPPJ","Gap":-51571946.6577109396,"SO H-2":63635818.0199999288}
{"Nama Depo":"Depo Tanjung","NIK SAC":17200519965,"Nama SAC":"Kisman Pidu","szEmployeeId":17210042412,"szname":"Muhammad Rizky Algifari","Dept":"ADD","Tipe Salesman":"Sales Representative Mix Yudistira","3LM":7616431.197039674,"Target":18400000,"Actual":13844200.2679089922,"Ach":0.7524021885,"vs 3LM":0.8176754847,"LOB":"GEN","GROUP":"GEN","Gap":-4555799.7320910078,"SO H-2":3067195.6000000001}
{"Nama Depo":"Depo Tanjung","NIK SAC":17200519965,"Nama SAC":"Kisman Pidu","szEmployeeId":17210042412,"szname":"Muhammad Rizky Algifari","Dept":"ACT","Tipe Salesman":"Sales Representative Mix Yudistira","3LM":43759015.1746250764,"Target":82000000,"Actual":55293214.8746789843,"Ach":0.6743074985,"vs 3LM":0.2635845358,"LOB":"GBS","GROUP":"GBS","Gap":-26706785.1253210157,"SO H-2":78424114.589999944}
{"Nama Depo":"Depo Tanjung","NIK SAC":17200519965,"Nama SAC":"Kisman Pidu","szEmployeeId":17210042412,"szname":"Muhammad Rizky Algifari","Dept":"ACT","Tipe Salesman":"Sales Representative Mix Yudistira","3LM":0.0,"Target":600000,"Actual":0.0,"Ach":0.0,"vs 3LM":0.0,"LOB":"HGJ","GROUP":"OTHERS","Gap":-600000.0,"SO H-2":0.0}
{"Nama Depo":"Depo Tanjung","NIK SAC":17200519965,"Nama SAC":"Kisman Pidu","szEmployeeId":17210036369,"szname":"Muhammad Tamrin","Dept":"ACT","Tipe Salesman":"Sales Representative Wholesaler Bima","3LM":30570479.8562846519,"Target":26000000,"Actual":42249421.6197999865,"Ach":1.6249777546,"vs 3LM":0.3820333151,"LOB":"MBR","GROUP":"MBR","Gap":16249421.6197999865,"SO H-2":2406534.2299999995}
{"Nama Depo":"Depo Tanjung","NIK SAC":17200519965,"Nama SAC":"Kisman Pidu","szEmployeeId":17210036369,"szname":"Muhammad Tamrin","Dept":"ACT","Tipe Salesman":"Sales Representative Wholesaler Bima","3LM":5418136.3900000015,"Target":18700000,"Actual":6373110.2599999942,"Ach":0.3408080353,"vs 3LM":0.1762550444,"LOB":"RANS","GROUP":"OTHERS","Gap":-12326889.7400000058,"SO H-2":2254187.2200000007}
{"Nama Depo":"Depo Tanjung","NIK SAC":17200519965,"Nama SAC":"Kisman Pidu","szEmployeeId":17210036369,"szname":"Muhammad Tamrin","Dept":"ACT","Tipe Salesman":"Sales Representative Wholesaler Bima","3LM":0.0,"Target":0,"Actual":0.0,"Ach":0.0,"vs 3LM":0.0,"LOB":"GSJ","GROUP":"OTHERS","Gap":0.0,"SO H-2":0.0}
{"Nama Depo":"Depo Tanjung","NIK SAC":17200519965,"Nama SAC":"Kisman Pidu","szEmployeeId":17210036369,"szname":"Muhammad Tamrin","Dept":"ACR","Tipe Salesman":"Sales Representative Wholesaler Bima","3LM":159515339.2299715877,"Target":179300000,"Actual":84795403.7194700092,"Ach":0.4729247279,"vs 3LM":-0.4684184974,"LOB":"GPPJ","GROUP":"GPPJ","Gap":-94504596.2805299908,"SO H-2":44042648.6100000218}
{"Nama Depo":"Depo Tanjung","NIK SAC":17200519965,"Nama SAC":"Kisman Pidu","szEmployeeId":17210036369,"szname":"Muhammad Tamrin","Dept":"ACR","Tipe Salesman":"Sales Representative Wholesaler Bima","3LM":189085440.6342054904,"Target":270000000,"Actual":159787057.2576836348,"Ach":0.5918039158,"vs 3LM":-0.1549478547,"LOB":"GBS","GROUP":"GBS","Gap":-110212942.7423163652,"SO H-2":63514036.0799999982}
{"Nama Depo":"Depo Tanjung","NIK SAC":17200519965,"Nama SAC":"Kisman Pidu","szEmployeeId":17210037632,"szname":"Robianor","Dept":"ADD","Tipe Salesman":"Sales Representative Mix Yudistira","3LM":142686188.5374411643,"Target":158000000,"Actual":157063399.1050418317,"Ach":0.9940721462,"vs 3LM":0.1007610527,"LOB":"GBS","GROUP":"GBS","Gap":-936600.8949581683,"SO H-2":63463397.3700000048}
{"Nama Depo":"Depo Tanjung","NIK SAC":17200519965,"Nama SAC":"Kisman Pidu","szEmployeeId":17210037632,"szname":"Robianor","Dept":"ADD","Tipe Salesman":"Sales Representative Mix Yudistira","3LM":127320.4344143334,"Target":700000,"Actual":0.0,"Ach":0.0,"vs 3LM":-1.0,"LOB":"HGJ","GROUP":"OTHERS","Gap":-700000.0,"SO H-2":0.0}
{"Nama Depo":"Depo Tanjung","NIK SAC":17200519965,"Nama SAC":"Kisman Pidu","szEmployeeId":17210037632,"szname":"Robianor","Dept":"ADD","Tipe Salesman":"Sales Representative Mix Yudistira","3LM":16692677.1109713316,"Target":23000000,"Actual":14529039.614854997,"Ach":0.6316973746,"vs 3LM":-0.1296159676,"LOB":"MBR","GROUP":"MBR","Gap":-8470960.385145003,"SO H-2":10077903.5499999989}
{"Nama Depo":"Depo Tanjung","NIK SAC":17200519965,"Nama SAC":"Kisman Pidu","szEmployeeId":17210037632,"szname":"Robianor","Dept":"ADD","Tipe Salesman":"Sales Representative Mix Yudistira","3LM":4271992.1799999997,"Target":11700000,"Actual":3649621.370000002,"Ach":0.3119334504,"vs 3LM":-0.1456863177,"LOB":"RANS","GROUP":"OTHERS","Gap":null,"SO H-2":null}
{"Nama Depo":"Depo Tanjung","NIK SAC":17200519965,"Nama SAC":"Kisman Pidu","szEmployeeId":17210037632,"szname":"Robianor","Dept":"ADD","Tipe Salesman":"Sales Representative Mix Yudistira","3LM":0.0,"Target":0,"Actual":0.0,"Ach":0.0,"vs 3LM":0.0,"LOB":"GSJ","GROUP":"OTHERS","Gap":null,"SO H-2":null}
{"Nama Depo":"Depo Tanjung","NIK SAC":17200519965,"Nama SAC":"Kisman Pidu","szEmployeeId":17210037632,"szname":"Robianor","Dept":"ADD","Tipe Salesman":"Sales Representative Mix Yudistira","3LM":404020023.2220468521,"Target":412000000,"Actual":262885068.5977726579,"Ach":0.6380705548,"vs 3LM":-0.3493266336,"LOB":"GPPJ","GROUP":"GPPJ","Gap":-149114931.4022273421,"SO H-2":106972061.2299999297}
{"Nama Depo":"Depo Tanjung","NIK SAC":17200519965,"Nama SAC":"Kisman Pidu","szEmployeeId":17210037632,"szname":"Robianor","Dept":"ADD","Tipe Salesman":"Sales Representative Mix Yudistira","3LM":30691736.7133316584,"Target":30300000,"Actual":14414563.2825040072,"Ach":0.4757281611,"vs 3LM":-0.5303438376,"LOB":"GEN","GROUP":"GEN","Gap":-15885436.7174959928,"SO H-2":7991194.7100000018}
{"Nama Depo":"Depo Tanjung","NIK SAC":17200519965,"Nama SAC":"Kisman Pidu","szEmployeeId":17210042423,"szname":"Siti Fatimah Hadijah","Dept":"ACT","Tipe Salesman":"Sales Representative Retailer Bima","3LM":16460330.8615580704,"Target":30700000,"Actual":18709660.0863459893,"Ach":0.609435182,"vs 3LM":0.1366515196,"LOB":"GPPJ","GROUP":"GPPJ","Gap":-11990339.9136540107,"SO H-2":3484034.4099999992}
{"Nama Depo":"Depo Tanjung","NIK SAC":17200519965,"Nama SAC":"Kisman Pidu","szEmployeeId":17210042423,"szname":"Siti Fatimah Hadijah","Dept":"ACT","Tipe Salesman":"Sales Representative Retailer Bima","3LM":22885892.942061346,"Target":40000000,"Actual":29546994.20508999,"Ach":0.7386748551,"vs 3LM":0.2910570839,"LOB":"GBS","GROUP":"GBS","Gap":-10453005.79491001,"SO H-2":4435763.25}
{"Nama Depo":"Depo Tanjung","NIK SAC":17200519965,"Nama SAC":"Kisman Pidu","szEmployeeId":17210042423,"szname":"Siti Fatimah Hadijah","Dept":"ACT","Tipe Salesman":"Sales Representative Retailer Bima","3LM":145179.9033333334,"Target":300000,"Actual":266436.04,"Ach":0.8881201333,"vs 3LM":0.8352129591,"LOB":"HGJ","GROUP":"OTHERS","Gap":-33563.96,"SO H-2":22202.67}
{"Nama Depo":"Depo Tanjung","NIK SAC":17200519965,"Nama SAC":"Kisman Pidu","szEmployeeId":17210042423,"szname":"Siti Fatimah Hadijah","Dept":"ACT","Tipe Salesman":"Sales Representative Retailer Bima","3LM":2636448.3487033355,"Target":4000000,"Actual":6571182.9102579979,"Ach":1.6427957276,"vs 3LM":1.4924375679,"LOB":"MBR","GROUP":"MBR","Gap":2571182.9102579979,"SO H-2":905732.39}
{"Nama Depo":"Depo Tanjung","NIK SAC":17200519965,"Nama SAC":"Kisman Pidu","szEmployeeId":17210042423,"szname":"Siti Fatimah Hadijah","Dept":"ACT","Tipe Salesman":"Sales Representative Retailer Bima","3LM":4297554.3133333288,"Target":5300000,"Actual":5575416.3900000006,"Ach":1.0519653566,"vs 3LM":0.2973463471,"LOB":"RANS","GROUP":"OTHERS","Gap":275416.3900000006,"SO H-2":2282595.0900000008}
{"Nama Depo":"Depo Tanjung","NIK SAC":17200519965,"Nama SAC":"Kisman Pidu","szEmployeeId":17210042423,"szname":"Siti Fatimah Hadijah","Dept":"ACT","Tipe Salesman":"Sales Representative Retailer Bima","3LM":18303.0033333333,"Target":0,"Actual":0.0,"Ach":0.0,"vs 3LM":-1.0,"LOB":"GSJ","GROUP":"OTHERS","Gap":null,"SO H-2":null}
{"Nama Depo":"Depo Tanjung","NIK SAC":17200519965,"Nama SAC":"Kisman Pidu","szEmployeeId":17210032876,"szname":"Asman","Dept":"ACQ","Tipe Salesman":"Sales Representative Wholesaler Arjuna","3LM":590100852.0930788517,"Target":586000000,"Actual":583438772.151945591,"Ach":0.995629304,"vs 3LM":-0.0112897311,"LOB":"GPPJ & GEN","GROUP":"GPPJ & GEN","Gap":-2561227.848054409,"SO H-2":114963255.939999938}
{"Nama Depo":"Depo Tanjung","NIK SAC":17200519965,"Nama SAC":"Kisman Pidu","szEmployeeId":17210041467,"szname":"Doli Purnama Sari","Dept":"ACS","Tipe Salesman":"Sales Representative Retailer Arjuna","3LM":148726974.8935403228,"Target":159000000,"Actual":137298883.9078368247,"Ach":0.8635149931,"vs 3LM":-0.0768393964,"LOB":"GPPJ & GEN","GROUP":"GPPJ & GEN","Gap":-21701116.0921631753,"SO H-2":113449144.9899998307}
{"Nama Depo":"Depo Tanjung","NIK SAC":17200519965,"Nama SAC":"Kisman Pidu","szEmployeeId":17210042412,"szname":"Muhammad Rizky Algifari","Dept":"ADD","Tipe Salesman":"Sales Representative Mix Yudistira","3LM":113727804.384766981,"Target":307400000,"Actual":251272253.6101980507,"Ach":0.817411365,"vs 3LM":1.2094179604,"LOB":"GPPJ & GEN","GROUP":"GPPJ & GEN","Gap":-56127746.3898019493,"SO H-2":93464415.3399999738}
{"Nama Depo":"Depo Tanjung","NIK SAC":17200519965,"Nama SAC":"Kisman Pidu","szEmployeeId":17210042412,"szname":"Muhammad Rizky Algifari","Dept":"ACT","Tipe Salesman":"Sales Representative Mix Yudistira","3LM":46096531.8757337481,"Target":99200000,"Actual":62592401.6284589842,"Ach":0.6309717906,"vs 3LM":0.3578548989,"LOB":"GBS & OTHERS","GROUP":"GBS & OTHERS","Gap":-36607598.3715410158,"SO H-2":83084836.039999947}
{"Nama Depo":"Depo Tanjung","NIK SAC":17200519965,"Nama SAC":"Kisman Pidu","szEmployeeId":17210037632,"szname":"Robianor","Dept":"ACT","Tipe Salesman":"Sales Representative Mix Yudistira","3LM":434711759.9353784919,"Target":442300000,"Actual":277299631.88027668,"Ach":0.6269492016,"vs 3LM":-0.3621069006,"LOB":"GPPJ & GEN","GROUP":"GPPJ & GEN","Gap":-165000368.11972332,"SO H-2":66703013.6199999303}
{"Nama Depo":"Depo Tanjung","NIK SAC":17200519965,"Nama SAC":"Kisman Pidu","szEmployeeId":17210037632,"szname":"Robianor","Dept":"ADD","Tipe Salesman":"Sales Representative Mix Yudistira","3LM":163778178.2628268301,"Target":193400000,"Actual":175242060.0898968279,"Ach":0.9061119963,"vs 3LM":0.0699963936,"LOB":"GBS & OTHERS","GROUP":"GBS & OTHERS","Gap":-18157939.9101031721,"SO H-2":83084836.039999947}
{"Nama Depo":"Depo Tanjung","NIK SAC":17200519965,"Nama SAC":"Kisman Pidu","szEmployeeId":17210037897,"szname":"Hindra","Dept":"ADD","Tipe Salesman":"Sales Representative Mix Yudistira","3LM":358905708.202190876,"Target":423300000,"Actual":346160700.5173140764,"Ach":0.8177668333,"vs 3LM":-0.0355107411,"LOB":"GPPJ & GEN","GROUP":"GPPJ & GEN","Gap":-77139299.4826859236,"SO H-2":107556684.6900000274}
{"Nama Depo":"Depo Tanjung","NIK SAC":17200519965,"Nama SAC":"Kisman Pidu","szEmployeeId":17210037897,"szname":"Hindra","Dept":"ACT","Tipe Salesman":"Sales Representative Mix Yudistira","3LM":165541838.9270032346,"Target":214400000,"Actual":137924444.3892322183,"Ach":0.6433043115,"vs 3LM":-0.1668302993,"LOB":"GBS & OTHERS","GROUP":"GBS & OTHERS","Gap":-76475555.6107677817,"SO H-2":73541300.9200000018}
{"Nama Depo":"Depo Tanjung","NIK SAC":17200519965,"Nama SAC":"Kisman Pidu","szEmployeeId":17210036369,"szname":"Muhammad Tamrin","Dept":"ACR","Tipe Salesman":"Sales Representative Wholesaler Bima","3LM":159515339.2299715877,"Target":179300000,"Actual":84795403.7194700092,"Ach":0.4729247279,"vs 3LM":-0.4684184974,"LOB":"GPPJ & GEN","GROUP":"GPPJ & GEN","Gap":-94504596.2805299908,"SO H-2":117049964.7799999267}
{"Nama Depo":"Depo Tanjung","NIK SAC":17200519965,"Nama SAC":"Kisman Pidu","szEmployeeId":17210036369,"szname":"Muhammad Tamrin","Dept":"ACR","Tipe Salesman":"Sales Representative Wholesaler Bima","3LM":225074056.880490154,"Target":314700000,"Actual":208409589.1374835968,"Ach":0.6622484561,"vs 3LM":-0.0740399315,"LOB":"GBS & OTHERS","GROUP":"GBS & OTHERS","Gap":-106290410.8625164032,"SO H-2":125041159.489999935}
{"Nama Depo":"Depo Tanjung","NIK SAC":17200519965,"Nama SAC":"Kisman Pidu","szEmployeeId":17210042423,"szname":"Siti Fatimah Hadijah","Dept":"ACT","Tipe Salesman":"Sales Representative Retailer Bima","3LM":16460330.8615580704,"Target":30700000,"Actual":18709660.0863459893,"Ach":0.609435182,"vs 3LM":0.1366515196,"LOB":"GPPJ & GEN","GROUP":"GPPJ & GEN","Gap":-11990339.9136540107,"SO H-2":118447290.3499999344}
{"Nama Depo":"Depo Tanjung","NIK SAC":17200519965,"Nama SAC":"Kisman Pidu","szEmployeeId":17210042423,"szname":"Siti Fatimah Hadijah","Dept":"ACT","Tipe Salesman":"Sales Representative Retailer Bima","3LM":29965075.5074313432,"Target":49600000,"Actual":41960029.5453479886,"Ach":0.8459683376,"vs 3LM":0.4002978079,"LOB":"GBS & OTHERS","GROUP":"GBS & OTHERS","Gap":-7639970.4546520114,"SO H-2":122883053.5999999344}
